odmcp/__init__.py
odmcp/cli.py
odmcp/client.py
odmcp/utils.py
odmcp/providers/__template__.py
odmcp/providers/ch_sbb.py
odmcp-0.1.28.dist-info/METADATA
odmcp-0.1.28.dist-info/WHEEL
odmcp-0.1.28.dist-info/entry_points.txt
odmcp-0.1.28.dist-info/licenses/LICENSE
odmcp-0.1.28.dist-info/RECORD
