Metadata-Version: 2.3
Name: odmcp
Version: 0.1.28
Summary: Python MCP servers exposing Open Data to compatible LLM clients.
Requires-Python: >=3.10
Requires-Dist: httpx>=0.28.0
Requires-Dist: mcp>=1.0.0
